pythonal/__init__.py
pythonal-0.0.2.dist-info/LICENSE
pythonal-0.0.2.dist-info/METADATA
pythonal-0.0.2.dist-info/WHEEL
pythonal-0.0.2.dist-info/top_level.txt
pythonal-0.0.2.dist-info/zip-safe
pythonal-0.0.2.dist-info/RECORD
