Metadata-Version: 2.1
Name: pythonal
Version: 0.0.2
Summary: Functional Python Library
Home-page: https://github.com/SagaraBattousai/pythonal.git
Author: James Calo
Author-email: jamesafcalo@gmail.com
License: UNKNOWN
Platform: UNKNOWN
Classifier: Programming Language :: Python :: 3.9
Classifier: License :: OSI Approved :: GNU General Public License v3 (GPLv3)
Classifier: Operating System :: OS Independent
Requires-Python: >=3.9
License-File: LICENSE
